hino/__init__.py
hino/hinoapi.py
hino-0.0.487.dist-info/LICENSE
hino-0.0.487.dist-info/METADATA
hino-0.0.487.dist-info/WHEEL
hino-0.0.487.dist-info/top_level.txt
hino-0.0.487.dist-info/RECORD
