Metadata-Version: 2.1
Name: hino
Version: 0.0.487
Summary: unofficial API package for Hino.
Home-page: https://github.com/Somespi/Hino/
Author: Someone
Author-email: 
License: MIT
Keywords: API,hino,unofficial,Hino
License-File: LICENSE
Requires-Dist: requests
